lukai/__init__.py
lukai/saver.py
lukai/test_lukai.py
lukai/test_saver.py
lukai/tfjs.py
lukai/proto/__init__.py
lukai/proto/aggregatorpb/__init__.py
lukai/proto/aggregatorpb/aggregator_pb2.py
lukai/proto/aggregatorpb/aggregator_pb2_grpc.py
lukai/proto/clientpb/__init__.py
lukai/proto/clientpb/client_pb2.py
lukai/proto/clientpb/client_pb2_grpc.py
lukai/proto/github/__init__.py
lukai/proto/github/com/__init__.py
lukai/proto/github/com/gogo/__init__.py
lukai/proto/github/com/gogo/protobuf/__init__.py
lukai/proto/github/com/gogo/protobuf/gogoproto/__init__.py
lukai/proto/github/com/gogo/protobuf/gogoproto/gogo_pb2.py
lukai/proto/github/com/gogo/protobuf/gogoproto/gogo_pb2_grpc.py
lukai/proto/github/com/luk_ai/__init__.py
lukai/proto/github/com/luk_ai/lukai/__init__.py
lukai/proto/github/com/luk_ai/lukai/protobuf/__init__.py
lukai/proto/github/com/luk_ai/lukai/protobuf/aggregatorpb/__init__.py
lukai/proto/github/com/luk_ai/lukai/protobuf/aggregatorpb/aggregator_pb2.py
lukai/proto/github/com/luk_ai/lukai/protobuf/aggregatorpb/aggregator_pb2_grpc.py
lukai/proto/github/com/luk_ai/lukai/protobuf/clientpb/__init__.py
lukai/proto/github/com/luk_ai/lukai/protobuf/clientpb/client_pb2.py
lukai/proto/github/com/luk_ai/lukai/protobuf/clientpb/client_pb2_grpc.py
lukai/proto/github/com/luk_ai/lukai/protobuf/managerpb/__init__.py
lukai/proto/github/com/luk_ai/lukai/protobuf/managerpb/manager_pb2.py
lukai/proto/github/com/luk_ai/lukai/protobuf/managerpb/manager_pb2_grpc.py
lukai/proto/github/com/luk_ai/lukai/protobuf/tensorflow/__init__.py
lukai/proto/github/com/luk_ai/lukai/protobuf/tensorflow/saver_pb2.py
lukai/proto/github/com/luk_ai/lukai/protobuf/tensorflow/saver_pb2_grpc.py
lukai/proto/github/com/luk_ai/lukai/protobuf/tensorflow/types_pb2.py
lukai/proto/github/com/luk_ai/lukai/protobuf/tensorflow/types_pb2_grpc.py
lukai/proto/managerpb/__init__.py
lukai/proto/managerpb/manager_pb2.py
lukai/proto/managerpb/manager_pb2_grpc.py
lukai-0.6.dist-info/METADATA
lukai-0.6.dist-info/RECORD
lukai-0.6.dist-info/WHEEL
lukai-0.6.dist-info/top_level.txt
