Metadata-Version: 2.1
Name: lukai
Version: 0.6
Summary: Luk.ai management library
Home-page: https://github.com/luk-ai/lukai/tree/master/py
Author: Tristan Rice
Author-email: rice@fn.lc
License: UNKNOWN
Keywords: ml,machine learning,lukai
Platform: UNKNOWN
Classifier: Programming Language :: Python :: 2
Classifier: Programming Language :: Python :: 3
Classifier: License :: OSI Approved :: MIT License
Classifier: Operating System :: OS Independent
Requires-Dist: grpcio
Requires-Dist: six
Requires-Dist: srvlookup
Requires-Dist: tensorflow (==1.8.0)
Requires-Dist: tensorflowjs
Requires-Dist: protobuf
